[
 {    
   "SKU": "COLOURS",    
   "DESIGN": "",    
   "DESCRIPTION": "",    
   "ACCORDION": "",    
   "PLATFORM": "",    
   "BARCODE": "",    
   "ORDER QTY PACK OF  6": "",    
   "FIELD8": "",    
   "FIELD9": "",    
   "STYLE": "Colours",    
   "STATUS": ""  
  },  
  {    
   "SKU": "101000 ",    
   "DESIGN": "",    
   "DESCRIPTION": "Black",    
   "ACCORDION": "Black ",    
   "PLATFORM": "Black",    
   "BARCODE": "859184004454",    
   "ORDER QTY PACK OF  6": "",    
   "FIELD8": "",    
   "FIELD9": "$0.00",    
   "STYLE": "Colours",    
   "STATUS": ""  
  },  
  {    
   "SKU": "101425 ",    
   "DESIGN": "",    
   "DESCRIPTION": "Cascade Water",    
   "ACCORDION": "Black",    
   "PLATFORM": "Black",    
   "BARCODE": "815373024191",    
   "ORDER QTY PACK OF  6": "",    
   "FIELD8": "",    
   "FIELD9": "$0.00",    
   "STYLE": "Colours",    
   "STATUS": ""  
  },  
  {    
   "SKU": "101027 ",    
   "DESIGN": "",    
   "DESCRIPTION": "The Sound",    
   "ACCORDION": "Black",    
   "PLATFORM": "Black",    
   "BARCODE": "859184004317",    
   "ORDER QTY PACK OF  6": "",    
   "FIELD8": "",    
   "FIELD9": "$0.00",    
   "STYLE": "Colours",    
   "STATUS": ""  
  },  
  {    
   "SKU": "101114 ",    
   "DESIGN": "",    
   "DESCRIPTION": "Blush",    
   "ACCORDION": "Grey",    
   "PLATFORM": "Grey",    
   "BARCODE": "815373020742",    
   "ORDER QTY PACK OF  6": "",    
   "FIELD8": "",    
   "FIELD9": "$0.00",    
   "STYLE": "Colours",    
   "STATUS": ""  
  },  
  {    
   "SKU": "101505 ",    
   "DESIGN": "",    
   "DESCRIPTION": "The Bomb",    
   "ACCORDION": "Grey",    
   "PLATFORM": "Grey",    
   "BARCODE": "815373025471",    
   "ORDER QTY PACK OF  6": "",    
   "FIELD8": "",    
   "FIELD9": "$0.00",    
   "STYLE": "Colours",    
   "STATUS": "NEW" 
  },  
  {    
   "SKU": "101536 ",    
   "DESIGN": "",    
   "DESCRIPTION": "Green Cameo",    
   "ACCORDION": "Black",    
   "PLATFORM": "Black",    
   "BARCODE": "815373025822",    
   "ORDER QTY PACK OF  6": "",    
   "FIELD8": "",    
   "FIELD9": "$0.00",    
   "STYLE": "Colours",    
   "STATUS": ""  
  },
  {
   "SKU": "MANDALAS",
   "DESIGN": "",
   "DESCRIPTION": "",
   "ACCORDION": "",
   "PLATFORM": "",
   "BARCODE": "",
   "ORDER QTY PACK OF  6": "",
   "FIELD8": "",
   "FIELD9": "",
   "STYLE": "MANDALAS",
   "STATUS": ""
 },
 {
   "SKU": "101174 ",
   "DESIGN": "",
   "DESCRIPTION": "Peace Sky",
   "ACCORDION": "Black",
   "PLATFORM": "Black",
   "BARCODE": "815373021336",
   "ORDER QTY PACK OF  6": "",
   "FIELD8": "",
   "FIELD9": "$0.00",
   "STYLE": "MANDALAS",
   "STATUS": ""
 },
 {
   "SKU": "101175 ",
   "DESIGN": "",
   "DESCRIPTION": "Peace Tiffany",
   "ACCORDION": "Grey",
   "PLATFORM": "Grey",
   "BARCODE": "815373021343",
   "ORDER QTY PACK OF  6": "",
   "FIELD8": "",
   "FIELD9": "$0.00",
   "STYLE": "MANDALAS",
   "STATUS": ""
 },
 {
   "SKU": "101253 ",
   "DESIGN": "",
   "DESCRIPTION": "Aztec Mandala Red",
   "ACCORDION": "Grey",
   "PLATFORM": "Grey",
   "BARCODE": "815373022272",
   "ORDER QTY PACK OF  6": "",
   "FIELD8": "",
   "FIELD9": "$0.00",
   "STYLE": "MANDALAS",
   "STATUS": ""
 },
 {
   "SKU": "101466 ",
   "DESIGN": "",
   "DESCRIPTION": "Golden Silence",
   "ACCORDION": "Grey",
   "PLATFORM": "Grey",
   "BARCODE": "815373024696",
   "ORDER QTY PACK OF  6": "",
   "FIELD8": "",
   "FIELD9": "$0.00",
   "STYLE": "MANDALAS",
   "STATUS": ""
 },
 {
   "SKU": "101128 ",
   "DESIGN": "",
   "DESCRIPTION": "Pakwan Sunset Ocean",
   "ACCORDION": "Black",
   "PLATFORM": "Black",
   "BARCODE": "815373020872",
   "ORDER QTY PACK OF  6": "",
   "FIELD8": "",
   "FIELD9": "$0.00",
   "STYLE": "MANDALAS",
   "STATUS": ""
 },
 {
   "SKU": "101828 ",
   "DESIGN": "",
   "DESCRIPTION": "Flower Mandala",
   "ACCORDION": "Grey",
   "PLATFORM": "Grey",
   "BARCODE": "842978104935",
   "ORDER QTY PACK OF  6": "",
   "FIELD8": "",
   "FIELD9": "$0.00",
   "STYLE": "MANDALAS",
   "STATUS": "NEW"
 },
 {
   "SKU": "101685 ",
   "DESIGN": "",
   "DESCRIPTION": "Golden Lace",
   "ACCORDION": "Black",
   "PLATFORM": "Black",
   "BARCODE": "842978100906",
   "ORDER QTY PACK OF  6": "",
   "FIELD8": "",
   "FIELD9": "$0.00",
   "STYLE": "MANDALAS",
   "STATUS": ""
 },
 {
   "SKU": "MARBLE",
   "DESIGN": "",
   "DESCRIPTION": "",
   "ACCORDION": "",
   "PLATFORM": "",
   "BARCODE": "",
   "ORDER QTY PACK OF  6": "",
   "FIELD8": "",
   "FIELD9": "",
   "STYLE": "MANDALAS",
   "STATUS": ""
 },
 {
   "SKU": "101178 ",
   "DESIGN": "",
   "DESCRIPTION": "White Marble",
   "ACCORDION": "Black",
   "PLATFORM": "Black",
   "BARCODE": "815373021374",
   "ORDER QTY PACK OF  6": "",
   "FIELD8": "",
   "FIELD9": "$0.00",
   "STYLE": "MANDALAS",
   "STATUS": ""
 },
 {
   "SKU": "101251 ",
   "DESIGN": "",
   "DESCRIPTION": "Black Marble",
   "ACCORDION": "Black ",
   "PLATFORM": "Black",
   "BARCODE": "815373022258",
   "ORDER QTY PACK OF  6": "",
   "FIELD8": "",
   "FIELD9": "$0.00",
   "STYLE": "MANDALAS",
   "STATUS": ""
 },
 {
   "SKU": "101331 ",
   "DESIGN": "",
   "DESCRIPTION": "Blood Marble",
   "ACCORDION": "Black ",
   "PLATFORM": "Black",
   "BARCODE": "815373023194",
   "ORDER QTY PACK OF  6": "",
   "FIELD8": "",
   "FIELD9": "$0.00",
   "STYLE": "MANDALAS",
   "STATUS": ""
 },
 {
   "SKU": "101335 ",
   "DESIGN": "",
   "DESCRIPTION": "Marble Chic ",
   "ACCORDION": "Grey",
   "PLATFORM": "Grey",
   "BARCODE": "815373023231",
   "ORDER QTY PACK OF  6": "",
   "FIELD8": "",
   "FIELD9": "$0.00",
   "STYLE": "",
   "STATUS": ""
 },
 {
   "SKU": "101444 ",
   "DESIGN": "",
   "DESCRIPTION": "Blue Marble",
   "ACCORDION": "Black",
   "PLATFORM": "Black",
   "BARCODE": "815373024405",
   "ORDER QTY PACK OF  6": "",
   "FIELD8": "",
   "FIELD9": "$0.00",
   "STYLE": "MANDALAS",
   "STATUS": ""
 },
 {
   "SKU": "101744 ",
   "DESIGN": "",
   "DESCRIPTION": "Opal",
   "ACCORDION": "Grey",
   "PLATFORM": "Grey",
   "BARCODE": "842978102337",
   "ORDER QTY PACK OF  6": "",
   "FIELD8": "",
   "FIELD9": "$0.00",
   "STYLE": "MANDALAS",
   "STATUS": "NEW"
 },
 {
   "SKU": "101738 ",
   "DESIGN": "",
   "DESCRIPTION": "Ghost Marble",
   "ACCORDION": "Black",
   "PLATFORM": "Black",
   "BARCODE": "842978102276",
   "ORDER QTY PACK OF  6": "",
   "FIELD8": "",
   "FIELD9": "$0.00",
   "STYLE": "MANDALAS",
   "STATUS": "NEW"
 },
 {
   "SKU": "101447 ",
   "DESIGN": "",
   "DESCRIPTION": "Ice Blue Agate",
   "ACCORDION": "Grey",
   "PLATFORM": "Grey",
   "BARCODE": "815373024504",
   "ORDER QTY PACK OF  6": "",
   "FIELD8": "",
   "FIELD9": "$0.00",
   "STYLE": "MANDALAS",
   "STATUS": ""
 },
 {
   "SKU": "GALACTIC",
   "DESIGN": "",
   "DESCRIPTION": "",
   "ACCORDION": "",
   "PLATFORM": "",
   "BARCODE": "",
   "ORDER QTY PACK OF  6": "",
   "FIELD8": "",
   "FIELD9": "",
   "STYLE": "",
   "STATUS": ""
 },
 {
   "SKU": "101106 ",
   "DESIGN": "",
   "DESCRIPTION": "Blue Nebula",
   "ACCORDION": "Black",
   "PLATFORM": "Black",
   "BARCODE": "815373020841",
   "ORDER QTY PACK OF  6": "",
   "FIELD8": "",
   "FIELD9": "$0.00",
   "STYLE": "GALACTIC",
   "STATUS": ""
 },
 {
   "SKU": "101690 ",
   "DESIGN": "",
   "DESCRIPTION": "Veil Nebula",
   "ACCORDION": "Black ",
   "PLATFORM": "Black",
   "BARCODE": "842978100951",
   "ORDER QTY PACK OF  6": "",
   "FIELD8": "",
   "FIELD9": "$0.00",
   "STYLE": "GALACTIC",
   "STATUS": ""
 },
 {
   "SKU": "101450 ",
   "DESIGN": "",
   "DESCRIPTION": "Out Of This World",
   "ACCORDION": "Grey",
   "PLATFORM": "Grey",
   "BARCODE": "815373024535",
   "ORDER QTY PACK OF  6": "",
   "FIELD8": "",
   "FIELD9": "$0.00",
   "STYLE": "GALACTIC",
   "STATUS": ""
 },
 {
   "SKU": "101819 ",
   "DESIGN": "",
   "DESCRIPTION": "Starry Constellation",
   "ACCORDION": "Grey",
   "PLATFORM": "Grey",
   "BARCODE": "842978104003",
   "ORDER QTY PACK OF  6": "",
   "FIELD8": "",
   "FIELD9": "$0.00",
   "STYLE": "GALACTIC",
   "STATUS": "NEW"
 },
 {
   "SKU": "101747 ",
   "DESIGN": "",
   "DESCRIPTION": "MonkeyHead Galaxy",
   "ACCORDION": "Grey",
   "PLATFORM": "Grey",
   "BARCODE": "842978102528",
   "ORDER QTY PACK OF  6": "",
   "FIELD8": "",
   "FIELD9": "$0.00",
   "STYLE": "GALACTIC",
   "STATUS": "NEW"
 },
 {
   "SKU": "800001 ",
   "DESIGN": "",
   "DESCRIPTION": "Space Doodles",
   "ACCORDION": "Grey",
   "PLATFORM": "Grey",
   "BARCODE": "842978110837",
   "ORDER QTY PACK OF  6": "",
   "FIELD8": "",
   "FIELD9": "$0.00",
   "STYLE": "GALACTIC",
   "STATUS": "NEW"
 },
 {
   "SKU": "800044 ",
   "DESIGN": "",
   "DESCRIPTION": "Saturn",
   "ACCORDION": "Grey",
   "PLATFORM": "Grey",
   "BARCODE": "842978110813",
   "ORDER QTY PACK OF  6": "",
   "FIELD8": "",
   "FIELD9": "$0.00",
   "STYLE": "GALACTIC",
   "STATUS": "NEW"
 },
 {
   "SKU": "ANIMALS",
   "DESIGN": "",
   "DESCRIPTION": "",
   "ACCORDION": "",
   "PLATFORM": "",
   "BARCODE": "",
   "ORDER QTY PACK OF  6": "",
   "FIELD8": "",
   "FIELD9": "",
   "STYLE": "",
   "STATUS": ""
 },
 {
   "SKU": "800021 ",
   "DESIGN": "",
   "DESCRIPTION": "Llamacorn",
   "ACCORDION": "Grey",
   "PLATFORM": "Grey",
   "BARCODE": "842978110585",
   "ORDER QTY PACK OF  6": "",
   "FIELD8": "",
   "FIELD9": "$0.00",
   "STYLE": "ANIMALS",
   "STATUS": "NEW"
 },
 {
   "SKU": "800025",
   "DESIGN": "",
   "DESCRIPTION": "Unicorn dreams",
   "ACCORDION": "Grey",
   "PLATFORM": "Grey",
   "BARCODE": "842978110622",
   "ORDER QTY PACK OF  6": "",
   "FIELD8": "",
   "FIELD9": "$0.00",
   "STYLE": "ANIMALS",
   "STATUS": "NEW"
 },
 {
   "SKU": "800027",
   "DESIGN": "",
   "DESCRIPTION": "Dreamer",
   "ACCORDION": "Grey",
   "PLATFORM": "Grey",
   "BARCODE": "842978110646",
   "ORDER QTY PACK OF  6": "",
   "FIELD8": "",
   "FIELD9": "$0.00",
   "STYLE": "ANIMALS",
   "STATUS": "NEW"
 },
 {
   "SKU": "101816",
   "DESIGN": "",
   "DESCRIPTION": "Furry Peru",
   "ACCORDION": "Grey",
   "PLATFORM": "Grey",
   "BARCODE": "842978103556",
   "ORDER QTY PACK OF  6": "",
   "FIELD8": "",
   "FIELD9": "$0.00",
   "STYLE": "ANIMALS",
   "STATUS": "NEW"
 },
 {
   "SKU": "101792",
   "DESIGN": "",
   "DESCRIPTION": "Bubble Gum Giraffe",
   "ACCORDION": "Grey",
   "PLATFORM": "Grey",
   "BARCODE": "842978103266",
   "ORDER QTY PACK OF  6": "",
   "FIELD8": "",
   "FIELD9": "$0.00",
   "STYLE": "ANIMALS",
   "STATUS": "NEW"
 },
 {
   "SKU": "800026",
   "DESIGN": "",
   "DESCRIPTION": "Pegasus Magic",
   "ACCORDION": "Grey",
   "PLATFORM": "Grey",
   "BARCODE": "842978110639",
   "ORDER QTY PACK OF  6": "",
   "FIELD8": "",
   "FIELD9": "$0.00",
   "STYLE": "ANIMALS",
   "STATUS": "NEW"
 },
 {
   "SKU": "800028 ",
   "DESIGN": "",
   "DESCRIPTION": "Unicone Bubblegum",
   "ACCORDION": "Grey",
   "PLATFORM": "Grey",
   "BARCODE": "842978110653",
   "ORDER QTY PACK OF  6": "",
   "FIELD8": "",
   "FIELD9": "$0.00",
   "STYLE": "ANIMALS",
   "STATUS": "NEW"
 },
 {
   "SKU": "101736 ",
   "DESIGN": "",
   "DESCRIPTION": "Born Free",
   "ACCORDION": "Black ",
   "PLATFORM": "Black",
   "BARCODE": "842978102252",
   "ORDER QTY PACK OF  6": "",
   "FIELD8": "",
   "FIELD9": "$0.00",
   "STYLE": "ANIMALS",
   "STATUS": "NEW"
 },
 {
   "SKU": "800034 ",
   "DESIGN": "",
   "DESCRIPTION": "Crying Tiger",
   "ACCORDION": "Black",
   "PLATFORM": "Black",
   "BARCODE": "842978110714",
   "ORDER QTY PACK OF  6": "",
   "FIELD8": "",
   "FIELD9": "$0.00",
   "STYLE": "ANIMALS",
   "STATUS": "NEW"
 },
 {
   "SKU": "101793 ",
   "DESIGN": "",
   "DESCRIPTION": "Shark",
   "ACCORDION": "Black",
   "PLATFORM": "Black",
   "BARCODE": "842978103273",
   "ORDER QTY PACK OF  6": "",
   "FIELD8": "",
   "FIELD9": "$0.00",
   "STYLE": "ANIMALS",
   "STATUS": "NEW"
 },
 {
   "SKU": "800035 ",
   "DESIGN": "",
   "DESCRIPTION": "Snake Rose",
   "ACCORDION": "Black",
   "PLATFORM": "Black",
   "BARCODE": "842978110721",
   "ORDER QTY PACK OF  6": "",
   "FIELD8": "",
   "FIELD9": "$0.00",
   "STYLE": "ANIMALS",
   "STATUS": "NEW"
 },
 {
   "SKU": "101461 ",
   "DESIGN": "",
   "DESCRIPTION": "Stargazing ",
   "ACCORDION": "Black",
   "PLATFORM": "Black",
   "BARCODE": "815373024672",
   "ORDER QTY PACK OF  6": "",
   "FIELD8": "",
   "FIELD9": "$0.00",
   "STYLE": "ANIMALS",
   "STATUS": ""
 },
 {
   "SKU": "101263 ",
   "DESIGN": "",
   "DESCRIPTION": "Kermit",
   "ACCORDION": "Black",
   "PLATFORM": "Black",
   "BARCODE": "815373022463",
   "ORDER QTY PACK OF  6": "",
   "FIELD8": "",
   "FIELD9": "$0.00",
   "STYLE": "ANIMALS",
   "STATUS": ""
 },
 {
   "SKU": "101380 ",
   "DESIGN": "",
   "DESCRIPTION": "Turtle",
   "ACCORDION": "Grey",
   "PLATFORM": "Grey",
   "BARCODE": "815373023743",
   "ORDER QTY PACK OF  6": "",
   "FIELD8": "",
   "FIELD9": "$0.00",
   "STYLE": "ANIMALS",
   "STATUS": ""
 },
 {
   "SKU": "101465 ",
   "DESIGN": "",
   "DESCRIPTION": "Unicat",
   "ACCORDION": "Black ",
   "PLATFORM": "Black",
   "BARCODE": "815373024689",
   "ORDER QTY PACK OF  6": "",
   "FIELD8": "",
   "FIELD9": "$0.00",
   "STYLE": "ANIMALS",
   "STATUS": ""
 },
 {
   "SKU": "101445 ",
   "DESIGN": "",
   "DESCRIPTION": "Wolf",
   "ACCORDION": "Grey",
   "PLATFORM": "Grey",
   "BARCODE": "815373024481",
   "ORDER QTY PACK OF  6": "",
   "FIELD8": "",
   "FIELD9": "$0.00",
   "STYLE": "ANIMALS",
   "STATUS": ""
 },
 {
   "SKU": "101271 ",
   "DESIGN": "",
   "DESCRIPTION": "Fox",
   "ACCORDION": "Grey",
   "PLATFORM": "Grey",
   "BARCODE": "815373022555",
   "ORDER QTY PACK OF  6": "",
   "FIELD8": "",
   "FIELD9": "$0.00",
   "STYLE": "ANIMALS",
   "STATUS": ""
 },
 {
   "SKU": "SPORTS",
   "DESIGN": "",
   "DESCRIPTION": "",
   "ACCORDION": "",
   "PLATFORM": "",
   "BARCODE": "",
   "ORDER QTY PACK OF  6": "",
   "FIELD8": "",
   "FIELD9": "",
   "STYLE": "",
   "STATUS": ""
 },
 {
   "SKU": "101036 ",
   "DESIGN": "",
   "DESCRIPTION": "Soccer Ball",
   "ACCORDION": "Black ",
   "PLATFORM": "Black",
   "BARCODE": "815373020049",
   "ORDER QTY PACK OF  6": "",
   "FIELD8": "",
   "FIELD9": "$0.00",
   "STYLE": "SPORTS",
   "STATUS": ""
 },
 {
   "SKU": "101181 ",
   "DESIGN": "",
   "DESCRIPTION": "Baseball",
   "ACCORDION": "Black ",
   "PLATFORM": "Black",
   "BARCODE": "815373021473",
   "ORDER QTY PACK OF  6": "",
   "FIELD8": "",
   "FIELD9": "$0.00",
   "STYLE": "SPORTS",
   "STATUS": ""
 },
 {
   "SKU": "101306 ",
   "DESIGN": "",
   "DESCRIPTION": "Tennis Ball",
   "ACCORDION": "Black ",
   "PLATFORM": "Black",
   "BARCODE": "815373022906",
   "ORDER QTY PACK OF  6": "",
   "FIELD8": "",
   "FIELD9": "$0.00",
   "STYLE": "SPORTS",
   "STATUS": ""
 },
 {
   "SKU": "101045 ",
   "DESIGN": "",
   "DESCRIPTION": "BaseBall",
   "ACCORDION": "Black ",
   "PLATFORM": "Black",
   "BARCODE": "815373020032",
   "ORDER QTY PACK OF  6": "",
   "FIELD8": "",
   "FIELD9": "$0.00",
   "STYLE": "SPORTS",
   "STATUS": ""
 },
 {
   "SKU": "101130 ",
   "DESIGN": "",
   "DESCRIPTION": "Golf",
   "ACCORDION": "Black ",
   "PLATFORM": "Black",
   "BARCODE": "815373020896",
   "ORDER QTY PACK OF  6": "",
   "FIELD8": "",
   "FIELD9": "$0.00",
   "STYLE": "SPORTS",
   "STATUS": "New"
 },
 {
   "SKU": "TRENDING",
   "DESIGN": "",
   "DESCRIPTION": "",
   "ACCORDION": "",
   "PLATFORM": "",
   "BARCODE": "",
   "ORDER QTY PACK OF  6": "",
   "FIELD8": "",
   "FIELD9": "",
   "STYLE": "",
   "STATUS": ""
 },
 {
   "SKU": "101257 ",
   "DESIGN": "",
   "DESCRIPTION": "Pink Donut",
   "ACCORDION": "White",
   "PLATFORM": "White",
   "BARCODE": "8153730232371",
   "ORDER QTY PACK OF  6": "",
   "FIELD8": "",
   "FIELD9": "$0.00",
   "STYLE": "TRENDING",
   "STATUS": ""
 },
 {
   "SKU": "101345 ",
   "DESIGN": "",
   "DESCRIPTION": "Illuminati",
   "ACCORDION": "Black",
   "PLATFORM": "Black",
   "BARCODE": "815373023330",
   "ORDER QTY PACK OF  6": "",
   "FIELD8": "",
   "FIELD9": "$0.00",
   "STYLE": "TRENDING",
   "STATUS": ""
 },
 {
   "SKU": "101689 ",
   "DESIGN": "",
   "DESCRIPTION": "Stony Heart",
   "ACCORDION": "Black",
   "PLATFORM": "Black",
   "BARCODE": "842978100944",
   "ORDER QTY PACK OF  6": "",
   "FIELD8": "",
   "FIELD9": "$0.00",
   "STYLE": "TRENDING",
   "STATUS": "NEW"
 },
 {
   "SKU": "101381 ",
   "DESIGN": "",
   "DESCRIPTION": "Stony Heart",
   "ACCORDION": "Grey",
   "PLATFORM": "Grey",
   "BARCODE": "815373023750",
   "ORDER QTY PACK OF  6": "",
   "FIELD8": "",
   "FIELD9": "$0.00",
   "STYLE": "TRENDING",
   "STATUS": ""
 },
 {
   "SKU": "101460 ",
   "DESIGN": "",
   "DESCRIPTION": "French Lace",
   "ACCORDION": "Grey",
   "PLATFORM": "Grey",
   "BARCODE": "815373024634",
   "ORDER QTY PACK OF  6": "",
   "FIELD8": "",
   "FIELD9": "$0.00",
   "STYLE": "TRENDING",
   "STATUS": ""
 },
 {
   "SKU": "101240 ",
   "DESIGN": "",
   "DESCRIPTION": "Yin Yang Roses",
   "ACCORDION": "Grey",
   "PLATFORM": "Grey",
   "BARCODE": "815373022142",
   "ORDER QTY PACK OF  6": "",
   "FIELD8": "",
   "FIELD9": "$0.00",
   "STYLE": "TRENDING",
   "STATUS": ""
 },
 {
   "SKU": "101392 ",
   "DESIGN": "",
   "DESCRIPTION": "Dope ",
   "ACCORDION": "Black",
   "PLATFORM": "Black",
   "BARCODE": "815373023866",
   "ORDER QTY PACK OF  6": "",
   "FIELD8": "",
   "FIELD9": "$0.00",
   "STYLE": "TRENDING",
   "STATUS": ""
 },
 {
   "SKU": "101394 ",
   "DESIGN": "",
   "DESCRIPTION": "Shut UP ",
   "ACCORDION": "White ",
   "PLATFORM": "White",
   "BARCODE": "815373023880",
   "ORDER QTY PACK OF  6": "",
   "FIELD8": "",
   "FIELD9": "$0.00",
   "STYLE": "TRENDING",
   "STATUS": ""
 },
 {
   "SKU": "FLORAL",
   "DESIGN": "",
   "DESCRIPTION": "",
   "ACCORDION": "",
   "PLATFORM": "",
   "BARCODE": "",
   "ORDER QTY PACK OF  6": "",
   "FIELD8": "",
   "FIELD9": "",
   "STYLE": "",
   "STATUS": ""
 },
 {
   "SKU": "800010 ",
   "DESIGN": "",
   "DESCRIPTION": "Daisies",
   "ACCORDION": "Grey",
   "PLATFORM": "Grey",
   "BARCODE": "842978110479",
   "ORDER QTY PACK OF  6": "",
   "FIELD8": "",
   "FIELD9": "$0.00",
   "STYLE": "FLORAL",
   "STATUS": "NEW"
 },
 {
   "SKU": "101371 ",
   "DESIGN": "",
   "DESCRIPTION": "Vintage Perfume",
   "ACCORDION": "Grey",
   "PLATFORM": "Grey",
   "BARCODE": "815373023651",
   "ORDER QTY PACK OF  6": "",
   "FIELD8": "",
   "FIELD9": "$0.00",
   "STYLE": "FLORAL",
   "STATUS": "NEW"
 },
 {
   "SKU": "101233 ",
   "DESIGN": "",
   "DESCRIPTION": "Pineapple Pattern",
   "ACCORDION": "Black ",
   "PLATFORM": "Black",
   "BARCODE": "815373022074",
   "ORDER QTY PACK OF  6": "",
   "FIELD8": "",
   "FIELD9": "$0.00",
   "STYLE": "FLORAL",
   "STATUS": ""
 },
 {
   "SKU": "800011 ",
   "DESIGN": "",
   "DESCRIPTION": "Paper flowers",
   "ACCORDION": "Grey",
   "PLATFORM": "Grey",
   "BARCODE": "842978110486",
   "ORDER QTY PACK OF  6": "",
   "FIELD8": "",
   "FIELD9": "$0.00",
   "STYLE": "FLORAL",
   "STATUS": "NEW"
 },
 {
   "SKU": "800023 ",
   "DESIGN": "",
   "DESCRIPTION": "Boho Skull",
   "ACCORDION": "Grey",
   "PLATFORM": "Grey",
   "BARCODE": "842978110608",
   "ORDER QTY PACK OF  6": "",
   "FIELD8": "",
   "FIELD9": "$0.00",
   "STYLE": "FLORAL",
   "STATUS": "NEW"
 },
 {
   "SKU": "101230 ",
   "DESIGN": "",
   "DESCRIPTION": "Palm Trees",
   "ACCORDION": "White ",
   "PLATFORM": "White",
   "BARCODE": "8153730220043",
   "ORDER QTY PACK OF  6": "",
   "FIELD8": "",
   "FIELD9": "$0.00",
   "STYLE": "FLORAL",
   "STATUS": ""
 },
 {
   "SKU": "101029 ",
   "DESIGN": "",
   "DESCRIPTION": "Floral Black",
   "ACCORDION": "Black ",
   "PLATFORM": "Black",
   "BARCODE": "859184004706",
   "ORDER QTY PACK OF  6": "",
   "FIELD8": "",
   "FIELD9": "$0.00",
   "STYLE": "FLORAL",
   "STATUS": ""
 },
 {
   "SKU": "101231 ",
   "DESIGN": "",
   "DESCRIPTION": "Hibiscus",
   "ACCORDION": "Black ",
   "PLATFORM": "Black",
   "BARCODE": "815373022050",
   "ORDER QTY PACK OF  6": "",
   "FIELD8": "",
   "FIELD9": "$0.00",
   "STYLE": "FLORAL",
   "STATUS": ""
 },
 {
   "SKU": "101737 ",
   "DESIGN": "",
   "DESCRIPTION": "Palm Shadows",
   "ACCORDION": "Grey",
   "PLATFORM": "Grey",
   "BARCODE": "842978102269",
   "ORDER QTY PACK OF  6": "",
   "FIELD8": "",
   "FIELD9": "$0.00",
   "STYLE": "FLORAL",
   "STATUS": "NEW"
 },
 {
   "SKU": "SUMMER",
   "DESIGN": "",
   "DESCRIPTION": "",
   "ACCORDION": "",
   "PLATFORM": "",
   "BARCODE": "",
   "ORDER QTY PACK OF  6": "",
   "FIELD8": "",
   "FIELD9": "",
   "STYLE": "SUMMER",
   "STATUS": ""
 },
 {
   "SKU": "101021 ",
   "DESIGN": "",
   "DESCRIPTION": "Wave",
   "ACCORDION": "Black ",
   "PLATFORM": "Black",
   "BARCODE": "859184004287",
   "ORDER QTY PACK OF  6": "",
   "FIELD8": "",
   "FIELD9": "$0.00",
   "STYLE": "SUMMER",
   "STATUS": ""
 },
 {
   "SKU": "101218 ",
   "DESIGN": "",
   "DESCRIPTION": "Really Mermaid",
   "ACCORDION": "Black ",
   "PLATFORM": "Black",
   "BARCODE": "815373021923",
   "ORDER QTY PACK OF  6": "",
   "FIELD8": "",
   "FIELD9": "$0.00",
   "STYLE": "SUMMER",
   "STATUS": ""
 },
 {
   "SKU": "101274 ",
   "DESIGN": "",
   "DESCRIPTION": "Faux Abalone",
   "ACCORDION": "Black ",
   "PLATFORM": "Black",
   "BARCODE": "815373022586",
   "ORDER QTY PACK OF  6": "",
   "FIELD8": "",
   "FIELD9": "$0.00",
   "STYLE": "SUMMER",
   "STATUS": ""
 },
 {
   "SKU": "101234 ",
   "DESIGN": "",
   "DESCRIPTION": "Good Vibes ",
   "ACCORDION": "Black ",
   "PLATFORM": "Black",
   "BARCODE": "815373022081",
   "ORDER QTY PACK OF  6": "",
   "FIELD8": "",
   "FIELD9": "$0.00",
   "STYLE": "SUMMER",
   "STATUS": ""
 },
 {
   "SKU": "101329 ",
   "DESIGN": "",
   "DESCRIPTION": "Pink Teal Geode ",
   "ACCORDION": "White ",
   "PLATFORM": "White ",
   "BARCODE": "815373023170",
   "ORDER QTY PACK OF  6": "",
   "FIELD8": "",
   "FIELD9": "$0.00",
   "STYLE": "SUMMER",
   "STATUS": ""
 },
 {
   "SKU": "101238 ",
   "DESIGN": "",
   "DESCRIPTION": "Ocean From The Air",
   "ACCORDION": "Grey",
   "PLATFORM": "Grey",
   "BARCODE": "815373022128",
   "ORDER QTY PACK OF  6": "",
   "FIELD8": "",
   "FIELD9": "$0.00",
   "STYLE": "SUMMER",
   "STATUS": ""
 },
 {
   "SKU": "EYE BENDER",
   "DESIGN": "",
   "DESCRIPTION": "",
   "ACCORDION": "",
   "PLATFORM": "",
   "BARCODE": "",
   "ORDER QTY PACK OF  6": "",
   "FIELD8": "",
   "FIELD9": "",
   "STYLE": "",
   "STATUS": ""
 },
 {
   "SKU": "800009 ",
   "DESIGN": "",
   "DESCRIPTION": "Radiate",
   "ACCORDION": "Grey",
   "PLATFORM": "Grey",
   "BARCODE": "842978111841",
   "ORDER QTY PACK OF  6": "",
   "FIELD8": "",
   "FIELD9": "$0.00",
   "STYLE": "EYE BENDER",
   "STATUS": "NEW"
 },
 {
   "SKU": "101883 ",
   "DESIGN": "",
   "DESCRIPTION": "Twisted",
   "ACCORDION": "Black ",
   "PLATFORM": "Black",
   "BARCODE": "842978106595",
   "ORDER QTY PACK OF  6": "",
   "FIELD8": "",
   "FIELD9": "$0.00",
   "STYLE": "EYE BENDER",
   "STATUS": "NEW"
 },
 {
   "SKU": "FLAGS",
   "DESIGN": "",
   "DESCRIPTION": "",
   "ACCORDION": "",
   "PLATFORM": "",
   "BARCODE": "",
   "ORDER QTY PACK OF  6": "",
   "FIELD8": "",
   "FIELD9": "",
   "STYLE": "FLAGS",
   "STATUS": ""
 },
 {
   "SKU": "101145 ",
   "DESIGN": "",
   "DESCRIPTION": "English Flag",
   "ACCORDION": "Black",
   "PLATFORM": "Black",
   "BARCODE": "81537302104",
   "ORDER QTY PACK OF  6": "",
   "FIELD8": "",
   "FIELD9": "$0.00",
   "STYLE": "FLAGS",
   "STATUS": ""
 },
 {
   "SKU": "101049 ",
   "DESIGN": "",
   "DESCRIPTION": "Canada",
   "ACCORDION": "White",
   "PLATFORM": "White",
   "BARCODE": "815373020070",
   "ORDER QTY PACK OF  6": "",
   "FIELD8": "",
   "FIELD9": "$0.00",
   "STYLE": "FLAGS",
   "STATUS": ""
 },
 {
   "SKU": "101116 ",
   "DESIGN": "",
   "DESCRIPTION": "France",
   "ACCORDION": "White",
   "PLATFORM": "White",
   "BARCODE": "815373020667",
   "ORDER QTY PACK OF  6": "",
   "FIELD8": "",
   "FIELD9": "$0.00",
   "STYLE": "FLAGS",
   "STATUS": ""
 },
 {
   "SKU": "101115 ",
   "DESIGN": "",
   "DESCRIPTION": "Mexico",
   "ACCORDION": "White",
   "PLATFORM": "White",
   "BARCODE": "815373020650",
   "ORDER QTY PACK OF  6": "",
   "FIELD8": "",
   "FIELD9": "$0.00",
   "STYLE": "FLAGS",
   "STATUS": ""
 },
 {
   "SKU": "101093 ",
   "DESIGN": "",
   "DESCRIPTION": "Germany",
   "ACCORDION": "Black ",
   "PLATFORM": "Black",
   "BARCODE": "815373020520",
   "ORDER QTY PACK OF  6": "",
   "FIELD8": "",
   "FIELD9": "$0.00",
   "STYLE": "FLAGS",
   "STATUS": ""
 },
 {
   "SKU": "ALUMINUM",
   "DESIGN": "",
   "DESCRIPTION": "",
   "ACCORDION": "",
   "PLATFORM": "",
   "BARCODE": "",
   "ORDER QTY PACK OF  6": "",
   "FIELD8": "",
   "FIELD9": "",
   "STYLE": "",
   "STATUS": ""
 },
 {
   "SKU": "101141 ",
   "DESIGN": "",
   "DESCRIPTION": "Black Aluminum",
   "ACCORDION": "Black",
   "PLATFORM": "Black",
   "BARCODE": "815373021008",
   "ORDER QTY PACK OF  6": "",
   "FIELD8": "",
   "FIELD9": "$0.00",
   "STYLE": "ALUMINUM",
   "STATUS": ""
 },
 {
   "SKU": "101122 ",
   "DESIGN": "",
   "DESCRIPTION": "Gold Aluminum",
   "ACCORDION": "Black",
   "PLATFORM": "Black",
   "BARCODE": "815373020803",
   "ORDER QTY PACK OF  6": "",
   "FIELD8": "",
   "FIELD9": "$0.00",
   "STYLE": "ALUMINUM",
   "STATUS": ""
 },
 {
   "SKU": "101123 ",
   "DESIGN": "",
   "DESCRIPTION": "Rose Gold Aluminum",
   "ACCORDION": "Black",
   "PLATFORM": "Black",
   "BARCODE": "815373020810",
   "ORDER QTY PACK OF  6": "",
   "FIELD8": "",
   "FIELD9": "$0.00",
   "STYLE": "ALUMINUM",
   "STATUS": ""
 },
 {
   "SKU": "101124 ",
   "DESIGN": "",
   "DESCRIPTION": "Space Grey Aluminum",
   "ACCORDION": "Black",
   "PLATFORM": "Black",
   "BARCODE": "815373020827",
   "ORDER QTY PACK OF  6": "",
   "FIELD8": "",
   "FIELD9": "$0.00",
   "STYLE": "ALUMINUM",
   "STATUS": ""
 },
 {
   "SKU": "101125 ",
   "DESIGN": "",
   "DESCRIPTION": "Silver Aluminum",
   "ACCORDION": "Black",
   "PLATFORM": "Black",
   "BARCODE": "815373020834",
   "ORDER QTY PACK OF  6": "",
   "FIELD8": "",
   "FIELD9": "$0.00",
   "STYLE": "ALUMINUM",
   "STATUS": ""
 },
 {
   "SKU": "DIAMOND",
   "DESIGN": "",
   "DESCRIPTION": "",
   "ACCORDION": "",
   "PLATFORM": "",
   "BARCODE": "",
   "ORDER QTY PACK OF  6": "",
   "FIELD8": "",
   "FIELD9": "",
   "STYLE": "",
   "STATUS": ""
 },
 {
   "SKU": "101452 ",
   "DESIGN": "",
   "DESCRIPTION": "Black Metallic Diamond",
   "ACCORDION": "Black",
   "PLATFORM": "Black",
   "BARCODE": "815373024559",
   "ORDER QTY PACK OF  6": "",
   "FIELD8": "",
   "FIELD9": "$0.00",
   "STYLE": "DIAMOND",
   "STATUS": ""
 },
 {
   "SKU": "101676 ",
   "DESIGN": "",
   "DESCRIPTION": "Glacier Metallic Diamond",
   "ACCORDION": "Grey",
   "PLATFORM": "Grey",
   "BARCODE": "842978100807",
   "ORDER QTY PACK OF  6": "",
   "FIELD8": "",
   "FIELD9": "$0.00",
   "STYLE": "DIAMOND",
   "STATUS": ""
 },
 {
   "SKU": "101636 ",
   "DESIGN": "",
   "DESCRIPTION": "Rose Gold Metallic Diamond",
   "ACCORDION": "Grey",
   "PLATFORM": "Grey",
   "BARCODE": "815373029943",
   "ORDER QTY PACK OF  6": "",
   "FIELD8": "",
   "FIELD9": "$0.00",
   "STYLE": "DIAMOND",
   "STATUS": ""
 },
 {
   "SKU": "101677 ",
   "DESIGN": "",
   "DESCRIPTION": "Red Metallic Diamond",
   "ACCORDION": "Grey",
   "PLATFORM": "Grey",
   "BARCODE": "842978100814",
   "ORDER QTY PACK OF  6": "",
   "FIELD8": "",
   "FIELD9": "$0.00",
   "STYLE": "DIAMOND",
   "STATUS": ""
 },
 {
   "SKU": "Licensed: Harry Potter",
   "DESIGN": "",
   "DESCRIPTION": "",
   "ACCORDION": "",
   "PLATFORM": "",
   "BARCODE": "",
   "ORDER QTY PACK OF  6": "",
   "FIELD8": "",
   "FIELD9": "",
   "STYLE": "",
   "STATUS": ""
 },
 {
   "SKU": "101569 ",
   "DESIGN": "",
   "DESCRIPTION": "Hogwarts",
   "ACCORDION": "Black",
   "PLATFORM": "Black",
   "BARCODE": "815373028519",
   "ORDER QTY PACK OF  6": "",
   "FIELD8": "",
   "FIELD9": "$0.00",
   "STYLE": "Licensed: Harry Potter",
   "STATUS": "NEW"
 },
 {
   "SKU": "101571 ",
   "DESIGN": "",
   "DESCRIPTION": "Hufflepuff",
   "ACCORDION": "Black",
   "PLATFORM": "Black",
   "BARCODE": "815373028533",
   "ORDER QTY PACK OF  6": "",
   "FIELD8": "",
   "FIELD9": "$0.00",
   "STYLE": "Licensed: Harry Potter",
   "STATUS": "NEW"
 },
 {
   "SKU": "101572 ",
   "DESIGN": "",
   "DESCRIPTION": "Ravenclaw",
   "ACCORDION": "Black",
   "PLATFORM": "Black",
   "BARCODE": "815373028540",
   "ORDER QTY PACK OF  6": "",
   "FIELD8": "",
   "FIELD9": "$0.00",
   "STYLE": "Licensed: Harry Potter",
   "STATUS": "NEW"
 },
 {
   "SKU": "101566 ",
   "DESIGN": "",
   "DESCRIPTION": "Gryffindor",
   "ACCORDION": "Black",
   "PLATFORM": "Black",
   "BARCODE": "815373028489",
   "ORDER QTY PACK OF  6": "",
   "FIELD8": "",
   "FIELD9": "$0.00",
   "STYLE": "Licensed: Harry Potter",
   "STATUS": "NEW"
 },
 {
   "SKU": "101567 ",
   "DESIGN": "",
   "DESCRIPTION": "Slytherin",
   "ACCORDION": "Black",
   "PLATFORM": "Black",
   "BARCODE": "815373028496",
   "ORDER QTY PACK OF  6": "",
   "FIELD8": "",
   "FIELD9": "$0.00",
   "STYLE": "Licensed: Harry Potter",
   "STATUS": "NEW"
 },
 {
   "SKU": "Licensed: Pokemon",
   "DESIGN": "",
   "DESCRIPTION": "",
   "ACCORDION": "",
   "PLATFORM": "",
   "BARCODE": "",
   "ORDER QTY PACK OF  6": "",
   "FIELD8": "",
   "FIELD9": "",
   "STYLE": "Licensed: Pokemon",
   "STATUS": ""
 },
 {
   "SKU": "101492 ",
   "DESIGN": "",
   "DESCRIPTION": "Bulbasaur",
   "ACCORDION": "Black",
   "PLATFORM": "Black",
   "BARCODE": "815373025020",
   "ORDER QTY PACK OF  6": "",
   "FIELD8": "",
   "FIELD9": "$0.00",
   "STYLE": "Licensed: Pokemon",
   "STATUS": "NEW"
 },
 {
   "SKU": "101490 ",
   "DESIGN": "",
   "DESCRIPTION": "Poke Ball",
   "ACCORDION": "Black",
   "PLATFORM": "Black",
   "BARCODE": "815373025006",
   "ORDER QTY PACK OF  6": "",
   "FIELD8": "",
   "FIELD9": "$0.00",
   "STYLE": "Licensed: Pokemon",
   "STATUS": "NEW"
 },
 {
   "SKU": "101494 ",
   "DESIGN": "",
   "DESCRIPTION": "Squirtle",
   "ACCORDION": "Black",
   "PLATFORM": "Black",
   "BARCODE": "815373025044",
   "ORDER QTY PACK OF  6": "",
   "FIELD8": "",
   "FIELD9": "$0.00",
   "STYLE": "Licensed: Pokemon",
   "STATUS": "NEW"
 },
 {
   "SKU": "101491 ",
   "DESIGN": "",
   "DESCRIPTION": "Pikachu",
   "ACCORDION": "Black",
   "PLATFORM": "Black",
   "BARCODE": "815373025013",
   "ORDER QTY PACK OF  6": "",
   "FIELD8": "",
   "FIELD9": "$0.00",
   "STYLE": "Licensed: Pokemon",
   "STATUS": "NEW"
 },
 {
   "SKU": "101495 ",
   "DESIGN": "",
   "DESCRIPTION": "Charmander",
   "ACCORDION": "Black",
   "PLATFORM": "Black",
   "BARCODE": "815373025051",
   "ORDER QTY PACK OF  6": "",
   "FIELD8": "",
   "FIELD9": "$0.00",
   "STYLE": "Licensed: Pokemon",
   "STATUS": "NEW"
 },
 {
   "SKU": "101493 ",
   "DESIGN": "",
   "DESCRIPTION": "Eevee",
   "ACCORDION": "Black",
   "PLATFORM": "Black",
   "BARCODE": "815373025037",
   "ORDER QTY PACK OF  6": "",
   "FIELD8": "",
   "FIELD9": "$0.00",
   "STYLE": "Licensed: Pokemon",
   "STATUS": "NEW"
 },
 {
   "SKU": "Licensed: Keith Haring",
   "DESIGN": "",
   "DESCRIPTION": "",
   "ACCORDION": "",
   "PLATFORM": "",
   "BARCODE": "",
   "ORDER QTY PACK OF  6": "",
   "FIELD8": "",
   "FIELD9": "",
   "STYLE": "",
   "STATUS": ""
 },
 {
   "SKU": "101538 ",
   "DESIGN": "",
   "DESCRIPTION": "Untitled(Bros) Skateboarders",
   "ACCORDION": "Grey",
   "PLATFORM": "Grey",
   "BARCODE": "815373025846",
   "ORDER QTY PACK OF  6": "",
   "FIELD8": "",
   "FIELD9": "$0.00",
   "STYLE": "Licensed: Keith Haring",
   "STATUS": ""
 },
 {
   "SKU": "101541 ",
   "DESIGN": "",
   "DESCRIPTION": "3 Figures Holding A Heart",
   "ACCORDION": "Grey",
   "PLATFORM": "Grey",
   "BARCODE": "815373025877",
   "ORDER QTY PACK OF  6": "",
   "FIELD8": "",
   "FIELD9": "$0.00",
   "STYLE": "Licensed: Keith Haring",
   "STATUS": ""
 },
 {
   "SKU": "101539 ",
   "DESIGN": "",
   "DESCRIPTION": "Untitled (Torn) - Split Figure",
   "ACCORDION": "Grey",
   "PLATFORM": "Grey",
   "BARCODE": "815373025853",
   "ORDER QTY PACK OF  6": "",
   "FIELD8": "",
   "FIELD9": "$0.00",
   "STYLE": "Licensed: Keith Haring",
   "STATUS": ""
 },
 {
   "SKU": "101540 ",
   "DESIGN": "",
   "DESCRIPTION": "Figures In A Heart",
   "ACCORDION": "Black",
   "PLATFORM": "Black",
   "BARCODE": "815373025860",
   "ORDER QTY PACK OF  6": "",
   "FIELD8": "",
   "FIELD9": "$0.00",
   "STYLE": "Licensed: Keith Haring",
   "STATUS": ""
 },
 {
   "SKU": "PopMount, Combo Pack",
   "DESIGN": "",
   "DESCRIPTION": "",
   "ACCORDION": "",
   "PLATFORM": "",
   "BARCODE": "",
   "ORDER QTY PACK OF  6": "",
   "FIELD8": "",
   "FIELD9": "",
   "STYLE": "PopMount, Combo Pack",
   "STATUS": ""
 },
 {
   "SKU": "201000",
   "DESIGN": "",
   "DESCRIPTION": "PopMount",
   "ACCORDION": "Black",
   "PLATFORM": "",
   "BARCODE": "859184004867",
   "ORDER QTY PACK OF  6": "",
   "FIELD8": "",
   "FIELD9": "$0.00",
   "STYLE": "PopMount, Combo Pack",
   "STATUS": ""
 },
 {
   "SKU": "405000 ",
   "DESIGN": "",
   "DESCRIPTION": "Combo Pack (Black PC and Mount)",
   "ACCORDION": "Black",
   "PLATFORM": "Black",
   "BARCODE": "859184004904",
   "ORDER QTY PACK OF  6": "",
   "FIELD8": "",
   "FIELD9": "$0.00",
   "STYLE": "PopMount, Combo Pack",
   "STATUS": ""
 },
 {
   "SKU": "30100 ",
   "DESIGN": "",
   "DESCRIPTION": "Display",
   "ACCORDION": "",
   "PLATFORM": "",
   "BARCODE": "859184004881",
   "ORDER QTY PACK OF  6": "",
   "FIELD8": "",
   "FIELD9": "$0.00",
   "STYLE": "PopMount, Combo Pack",
   "STATUS": ""
 }
]
